compiled_cython/read_field.cp38-win_amd64.pyd
compiled_cython/read_phase_space.cp38-win_amd64.pyd
compiled_cython/read_tracking.cp38-win_amd64.pyd
lampy-0.5.0.dist-info/LICENSE.txt
lampy-0.5.0.dist-info/METADATA
lampy-0.5.0.dist-info/WHEEL
lampy-0.5.0.dist-info/top_level.txt
lampy-0.5.0.dist-info/RECORD
