Metadata-Version: 2.1
Name: lampy
Version: 0.5.0
Summary: Python suite to access, manipulate and plot ALaDyn data
Home-page: https://github.com/ALaDyn/ALaDyn
Author: ALaDyn Collaboration
Author-email: dterzani@lbl.gov
License: UNKNOWN
Project-URL: Bug Tracker, https://github.com/ALaDyn/tools-ALaDyn/issues
Platform: UNKNOWN
Classifier: Programming Language :: Python :: 3
Classifier: License :: OSI Approved :: GNU General Public License v3 (GPLv3)
Classifier: Operating System :: OS Independent
Classifier: Natural Language :: English
Classifier: Environment :: Console
Classifier: Intended Audience :: Science/Research
Classifier: Topic :: Scientific/Engineering :: Physics
Requires-Python: >=3.6
License-File: LICENSE.txt
Requires-Dist: Cython
Requires-Dist: numpy
Requires-Dist: matplotlib
Requires-Dist: scipy
Requires-Dist: f90nml
